sec_password/__init__.py
sec_password-0.1.2.dist-info/WHEEL
sec_password-0.1.2.dist-info/METADATA
sec_password-0.1.2.dist-info/RECORD
