Metadata-Version: 2.1
Name: sec-password
Version: 0.1.2
Summary: Secure Password library using only Python standard lib
Home-page: https://github.com/TomFaulkner/sec-password
Author: Tom Faulkner
Author-email: tomfaulkner@gmail.com
Requires-Python: >=3.8,<4.0
Classifier: Programming Language :: Python :: 3
Classifier: Programming Language :: Python :: 3.8
Classifier: Programming Language :: Python :: 3.9
